{
	"configurations" : 
	[
		{
			"directories" : 
			[
				{
					"build" : ".",
					"childIndexes" : 
					[
						1,
						2,
						3,
						4
					],
					"jsonFile" : "directory-.-Debug-f5ebdc15457944623624.json",
					"minimumCMakeVersion" : 
					{
						"string" : "3.11"
					},
					"projectIndex" : 0,
					"source" : "."
				},
				{
					"build" : "src",
					"jsonFile" : "directory-src-Debug-b6cf2213fc5053b67c22.json",
					"minimumCMakeVersion" : 
					{
						"string" : "3.11"
					},
					"parentIndex" : 0,
					"projectIndex" : 0,
					"source" : "src",
					"targetIndexes" : 
					[
						1
					]
				},
				{
					"build" : "apps",
					"jsonFile" : "directory-apps-Debug-76fddd1453400e648719.json",
					"minimumCMakeVersion" : 
					{
						"string" : "3.11"
					},
					"parentIndex" : 0,
					"projectIndex" : 0,
					"source" : "apps",
					"targetIndexes" : 
					[
						2
					]
				},
				{
					"build" : "tests",
					"jsonFile" : "directory-tests-Debug-b01f6abb0ab61427ef3b.json",
					"minimumCMakeVersion" : 
					{
						"string" : "3.11"
					},
					"parentIndex" : 0,
					"projectIndex" : 0,
					"source" : "tests",
					"targetIndexes" : 
					[
						0
					]
				},
				{
					"build" : "_deps/catch2-build",
					"jsonFile" : "directory-_deps.catch2-build-Debug-699497de59ed98ab9701.json",
					"minimumCMakeVersion" : 
					{
						"string" : "3.5"
					},
					"parentIndex" : 0,
					"projectIndex" : 1,
					"source" : "cmake/_deps/catch2-src"
				}
			],
			"name" : "Debug",
			"projects" : 
			[
				{
					"childIndexes" : 
					[
						1
					],
					"directoryIndexes" : 
					[
						0,
						1,
						2,
						3
					],
					"name" : "CppTicTacToe",
					"targetIndexes" : 
					[
						0,
						1,
						2
					]
				},
				{
					"directoryIndexes" : 
					[
						4
					],
					"name" : "Catch2",
					"parentIndex" : 0
				}
			],
			"targets" : 
			[
				{
					"directoryIndex" : 3,
					"id" : "test-tictactoe::@a44f0ac069e85531cdee",
					"jsonFile" : "target-test-tictactoe-Debug-a790ccc682c8e14b21f9.json",
					"name" : "test-tictactoe",
					"projectIndex" : 0
				},
				{
					"directoryIndex" : 1,
					"id" : "tictactoe::@145eef247bfb46b6828c",
					"jsonFile" : "target-tictactoe-Debug-9c315935bffccdcdd573.json",
					"name" : "tictactoe",
					"projectIndex" : 0
				},
				{
					"directoryIndex" : 2,
					"id" : "tictactoe-evaluator::@9e189ee61a034fc9b705",
					"jsonFile" : "target-tictactoe-evaluator-Debug-d008fbb7c140f5f983dc.json",
					"name" : "tictactoe-evaluator",
					"projectIndex" : 0
				}
			]
		}
	],
	"kind" : "codemodel",
	"paths" : 
	{
		"build" : "/home/jakub/Documents/dev/CPP_Code/CS126/cpp-TicTacToe/cmake",
		"source" : "/home/jakub/Documents/dev/CPP_Code/CS126/cpp-TicTacToe"
	},
	"version" : 
	{
		"major" : 2,
		"minor" : 3
	}
}
